{"@context":"http://greendelta.github.io/olca-schema/context.jsonld","@type":"Flow","@id":"c22645a2-3d85-458a-8391-d230e4972a75","name":"N-Methylolacrylamide","version":"00.00.000","category":{"@type":"Category","@id":"f1581141-87e2-3647-81ce-6fd43e3e34be","name":"unspecified"},"flowType":"ELEMENTARY_FLOW","cas":"924425.0","infrastructureFlow":false,"flowProperties":[{"@type":"FlowPropertyFactor","referenceFlowProperty":true,"flowProperty":{"@type":"FlowProperty","@id":"93a60a56-a3c8-11da-a746-0800200b9a66","name":"Mass"},"conversionFactor":1.0}]}