{"@context":"http://greendelta.github.io/olca-schema/context.jsonld","@type":"Flow","@id":"c963d2e1-0f08-3379-9f04-8cdebe2e5403","name":"ETHYL CHLOROACETATE","version":"00.00.000","category":{"@type":"Category","@id":"f1581141-87e2-3647-81ce-6fd43e3e34be","name":"unspecified"},"flowType":"ELEMENTARY_FLOW","cas":"105395.0","infrastructureFlow":false,"flowProperties":[{"@type":"FlowPropertyFactor","referenceFlowProperty":true,"flowProperty":{"@type":"FlowProperty","@id":"93a60a56-a3c8-11da-a746-0800200b9a66","name":"Mass"},"conversionFactor":1.0}]}