{"@context":"http://greendelta.github.io/olca-schema/context.jsonld","@type":"Source","@id":"c022c9b7-17f2-49de-82d8-1859c591f613","name":"EIA 2016","description":"Monthly Energy Review. Energy Information Administration","version":"00.00.002","lastChange":"2017-06-27T14:54:21.482-04:00","url":"http://www.eia.gov/totalenergy/data/monthly/","textReference":"EIA, 2016a. Monthly Energy Review. Energy Information Administration [WWW Document]. URL http://www.eia.gov/totalenergy/data/monthly/ (accessed 7.12.16).","year":2016}